yarbs.py
yarbs/__init__.py
yarbs/__main__.py
yarbs/yarbs.py
yarbs-0.4.1.dist-info/Copying.txt
yarbs-0.4.1.dist-info/METADATA
yarbs-0.4.1.dist-info/WHEEL
yarbs-0.4.1.dist-info/top_level.txt
yarbs-0.4.1.dist-info/RECORD
