Metadata-Version: 2.1
Name: yarbs
Version: 0.4.1
Summary: Create incremental backups using Rsync.
Home-page: https://gitlab.com/maranov/yarbs
Author: maranov
Author-email: maranov@outlook.com
License: WTFPL
Keywords: rsync backup
Platform: UNKNOWN
Classifier: Development Status :: 4 - Beta
Classifier: Intended Audience :: System Administrators
Classifier: Topic :: System :: Archiving :: Backup
Classifier: Programming Language :: Python :: 3.8
